{
    "Groups": [
        {
            "Name": "Main",
            "DisplayName": "Options",
            "Elements": [

                {
                    "Name": "IncludeDir0",
                    "DisplayName": "Stage Overrides",
                    "Description": [
                        "In certain stages in Sonic Generations and the Unleashed Project, settings for Sonic's physics have overrides. Adjust this option according to whether you are playing the standard game or the Unleashed Project to remove redundant overrides, allowing Sonic to handle more consistently. Or, set it to 'N/A' if you are not playing either of those (for example, a different stage mod).",
                    ],
                    "Type": "StageOptions",
                    "DefaultValue": "stages"
                },

                {
                    "Name": "IncludeDir2",
                    "DisplayName": "Classic Sonic Physics",
                    "Description": [
                        "Adjust Classic Sonic's physics settings.",
                    ],
                    "Type": "ClassicOptions",
                    "DefaultValue": "physicsc"
                },

                {
                    "Name": "IncludeDir1",
                    "DisplayName": "Modern Sonic Physics",
                    "Description": [
                        "Adjust Modern Sonic's physics settings and Homing Attack button.",
                    ],
                    "Type": "SonicOptions",
                    "DefaultValue": "physicsm"
                },
            ]
        }
    ],

    "Enums": {
        "StageOptions": [
            {
                "DisplayName": "Unleashed Project",
                "Value": "stages_unleashed",
                "Description": [
                    "Recommended for use with the Unleashed Project.",
                ]
            },

            {
                "DisplayName": "Sonic Generations",
                "Value": "stages",
                "Description": [
                    "Recommended for use with the standard game. This setting also addresses a glitch that can occur in Crisis City Act 2.",
                ]
            },

            {
                "DisplayName": "N/A",
                "Value": "dummy",
                "Description": [
                    "Load no modified stage files.",
                ]
            },
        ],

        "ClassicOptions": [
            {
                "DisplayName": "Alternate",
                "Value": "physicsc",
                "Description": [
                    "Use this mod's Classic Sonic physics settings. Handling will be similar to standard Generations with some differences like Spinning lasting longer.",
                ]
            },

            {
                "DisplayName": "N/A",
                "Value": "dummy",
                "Description": [
                    "Use the standard game's complete physics settings or settings from another mod.",
                ]
            },
        ],

        "SonicOptions": [
            {
                "DisplayName": "Unleashed w/Homing Attack on Boost",
                "Value": "physicsm",
                "Description": [
                    "Use Unleashed physics settings with the Homing Attack mapped to the Boost button.",
                ]
            },

            {
                "DisplayName": "Unleashed w/Homing Attack on Jump",
                "Value": "physicsm_abh",
                "Description": [
                    "Use Unleashed physics settings with the Homing Attack mapped to the Jump button.",
                ]
            },

            {
                "DisplayName": "Prototype w/Homing Attack on Boost",
                "Value": "physicsm_alt",
                "Description": [
                    "Use physics settings partially based on the Unleashed Preview Build with the Homing Attack mapped to the Boost button. Some differences include a higher jump, faster Wall Jump, and slower Light Speed Dash. Level design may not function as intended with these settings.",
                ]
            },

            {
                "DisplayName": "Prototype w/Homing Attack on Jump",
                "Value": "physicsm_alt_abh",
                "Description": [
                    "Use physics settings partially based on the Unleashed Preview Build with the Homing Attack mapped to the Jump button. Some differences include a higher jump, faster Wall Jump, and slower Light Speed Dash. Level design may not function as intended with these settings.",
                ]
            },

            {
                "DisplayName": "N/A",
                "Value": "dummy",
                "Description": [
                    "Use the standard game's complete physics settings or settings from another mod.",
                ]
            },
        ],
    },
  "IniFile": "mod.ini"
}
